scriptq/__main__.py
scriptq/gui.py
scriptq/settings.py
scriptq/graphics/blank.gif
scriptq/graphics/half_blank.gif
scriptq/graphics/insert.gif
scriptq/graphics/label_endeddone.gif
scriptq/graphics/label_endedfailed.gif
scriptq/graphics/label_endedstopped.gif
scriptq/graphics/label_queued.gif
scriptq/graphics/label_ready.gif
scriptq/graphics/label_running.gif
scriptq/graphics/move.gif
scriptq/graphics/next.gif
scriptq/graphics/remove.gif
scriptq/graphics/run.gif
scriptq/graphics/stop.gif
scriptq-1.2.dist-info/LICENSE
scriptq-1.2.dist-info/METADATA
scriptq-1.2.dist-info/WHEEL
scriptq-1.2.dist-info/top_level.txt
scriptq-1.2.dist-info/RECORD
