Metadata-Version: 2.1
Name: scriptq
Version: 1.2
Summary: Python script queuer
Home-page: https://github.com/mgely/scriptq
Author: Mario Gely
Author-email: mario.f.gely@gmail.com
License: UNKNOWN
Platform: UNKNOWN
Classifier: Programming Language :: Python :: 3
Classifier: License :: OSI Approved :: MIT License
Classifier: Operating System :: OS Independent
Requires-Python: >3.0.0
